shakenfist_agent/__init__.py
shakenfist_agent/_version.py
shakenfist_agent/main.py
shakenfist_agent/commandline/daemon.py
shakenfist_agent/protos/_copy_stubs.sh
shakenfist_agent/protos/agent.proto
shakenfist_agent/protos/agent_pb2.py
shakenfist_agent/protos/agent_pb2.pyi
shakenfist_agent/protos/agent_pb2_grpc.py
shakenfist_agent/protos/common.proto
shakenfist_agent/protos/common_pb2.py
shakenfist_agent/protos/common_pb2.pyi
shakenfist_agent/protos/common_pb2_grpc.py
shakenfist_agent/tests/__init__.py
shakenfist_agent/tests/test_daemon.py
shakenfist_agent-0.9.2.dist-info/licenses/AUTHORS
shakenfist_agent-0.9.2.dist-info/licenses/LICENSE
shakenfist_agent-0.9.2.dist-info/METADATA
shakenfist_agent-0.9.2.dist-info/WHEEL
shakenfist_agent-0.9.2.dist-info/entry_points.txt
shakenfist_agent-0.9.2.dist-info/top_level.txt
shakenfist_agent-0.9.2.dist-info/RECORD
